px4ctl/__init__.py
px4ctl/__main__.py
px4ctl/commands.py
px4ctl/mission.py
px4ctl/platforms/__init__.py
px4ctl/platforms/ardupilot.py
px4ctl/platforms/platform.py
px4ctl/platforms/px4.py
px4ctl/py.typed
px4ctl/storage.py
px4ctl-1.0.0a6.dist-info/entry_points.txt
px4ctl-1.0.0a6.dist-info/WHEEL
px4ctl-1.0.0a6.dist-info/METADATA
px4ctl-1.0.0a6.dist-info/RECORD
